{"elapsed":"0.084","endpoint-url":"https://raw.githubusercontent.com/digital-land/organisation-collection/main/data/local-authority.csv","entry-date":"2024-02-13T00:05:53.874080","request-headers":{"Accept":"*/*","Accept-Encoding":"gzip, deflate","Connection":"keep-alive","User-Agent":"DLUHC Digital Land"},"resource":"e11c68c5d2d0e2b91adf56e153ed539aa167e4c449a717eb9d7aded8a000f749","response-headers":{"Accept-Ranges":"bytes","Access-Control-Allow-Origin":"*","Cache-Control":"max-age=300","Connection":"keep-alive","Content-Encoding":"gzip","Content-Length":"22991","Content-Security-Policy":"default-src 'none'; style-src 'unsafe-inline'; sandbox","Content-Type":"text/plain; charset=utf-8","Cross-Origin-Resource-Policy":"cross-origin","Date":"Tue, 13 Feb 2024 00:05:54 GMT","ETag":"W/\"7e0c859004015031cb8ecc7c048c0f86007483d60e568d8676d702aa2c8dc649\"","Expires":"Tue, 13 Feb 2024 00:10:54 GMT","Source-Age":"0","Strict-Transport-Security":"max-age=31536000","Vary":"Authorization,Accept-Encoding,Origin","Via":"1.1 varnish","X-Cache":"MISS","X-Cache-Hits":"0","X-Content-Type-Options":"nosniff","X-Fastly-Request-ID":"230da5d2190d7f12bedfa3ae6281647b9d036796","X-Frame-Options":"deny","X-GitHub-Request-Id":"9E62:90A9:C41C7:E8B7A:65CAB261","X-Served-By":"cache-iad-kcgs7200092-IAD","X-Timer":"S1707782755.500011,VS0,VE70","X-XSS-Protection":"1; mode=block"},"ssl-verify":true,"status":"200"}