{"elapsed":"0.818","endpoint-url":"https://www.registers.service.gov.uk/registers/government-organisation/download-csv","entry-date":"2021-01-03T00:25:39.176552","request-headers":{"Accept":"*/*","Accept-Encoding":"gzip, deflate","Connection":"keep-alive","User-Agent":"Digital Land"},"resource":"cf49bc748be86776f0879995dab3a501c2a8af729782f4a58109d2097bdf0c2c","response-headers":{"Cache-Control":"private","Connection":"keep-alive","Content-Disposition":"attachment; filename=government-organisation.csv","Content-Transfer-Encoding":"binary","Content-Type":"application/csv; header=present","Date":"Sun, 03 Jan 2021 00:25:39 GMT","ETag":"W/\"cf49bc748be86776f0879995dab3a501\"","Referrer-Policy":"strict-origin-when-cross-origin","Set-Cookie":"seen_cookie_message=true; path=/; expires=Mon, 03 Jan 2022 00:25:39 GMT","Strict-Transport-Security":"max-age=31536000; includeSubDomains; preload","Transfer-Encoding":"chunked","Via":"1.1 4c3936cc7f5f36d3966cb34ebcbf91a7.cloudfront.net (CloudFront)","X-Amz-Cf-Id":"OznQQxr4SLfp3U1CLKcRKlrvV1OYr2eyYmvPjIymCJHB4Q1LdbcCGQ==","X-Amz-Cf-Pop":"IAD79-C1","X-Cache":"Miss from cloudfront","X-Content-Type-Options":"nosniff","X-Download-Options":"noopen","X-Frame-Options":"SAMEORIGIN","X-Permitted-Cross-Domain-Policies":"none","X-Request-Id":"c8dc99d0-d28b-4589-83eb-df58ddecec21","X-Runtime":"0.123568","X-Vcap-Request-Id":"f4ea97c6-afd6-43a3-7530-5c9f939cc8fe","X-Xss-Protection":"1; mode=block"},"ssl-verify":true,"status":"200"}