{"elapsed":"0.181","endpoint-url":"https://www.registers.service.gov.uk/registers/local-authority-eng/download-csv","entry-date":"2021-01-19T00:46:04.109653","request-headers":{"Accept":"*/*","Accept-Encoding":"gzip, deflate","Connection":"keep-alive","Cookie":"seen_cookie_message=true","User-Agent":"Digital Land"},"resource":"a878c850cb37f513c60560fcb3865952e936f7d8429330e6674652b2fcfb1566","response-headers":{"Cache-Control":"private","Connection":"keep-alive","Content-Disposition":"attachment; filename=local-authority-eng.csv","Content-Transfer-Encoding":"binary","Content-Type":"application/csv; header=present","Date":"Tue, 19 Jan 2021 00:46:05 GMT","ETag":"W/\"a878c850cb37f513c60560fcb3865952\"","Referrer-Policy":"strict-origin-when-cross-origin","Set-Cookie":"seen_cookie_message=true; path=/; expires=Wed, 19 Jan 2022 00:46:05 GMT","Strict-Transport-Security":"max-age=31536000; includeSubDomains; preload","Transfer-Encoding":"chunked","Via":"1.1 5d9ef69d47a63c80a41bbcf6902f6312.cloudfront.net (CloudFront)","X-Amz-Cf-Id":"3mFN_w6EB4J7EZZHFrfL7AB_qRt_iWrNai1m6FMZIkq-G57M7IWhKQ==","X-Amz-Cf-Pop":"IAD79-C1","X-Cache":"Miss from cloudfront","X-Content-Type-Options":"nosniff","X-Download-Options":"noopen","X-Frame-Options":"SAMEORIGIN","X-Permitted-Cross-Domain-Policies":"none","X-Request-Id":"27adc1d1-f638-4cfd-bdd9-f3e8e24b2280","X-Runtime":"0.079689","X-Vcap-Request-Id":"8a46ddd9-b0e6-4edc-6462-323d29ff759d","X-Xss-Protection":"1; mode=block"},"ssl-verify":true,"status":"200"}