{"elapsed":"0.074","endpoint-url":"https://raw.githubusercontent.com/digital-land/organisation-collection/main/data/public-authority.csv","entry-date":"2024-01-18T00:07:31.200767","request-headers":{"Accept":"*/*","Accept-Encoding":"gzip, deflate","Connection":"keep-alive","User-Agent":"DLUHC Digital Land"},"resource":"d33802428521bf8cb2e2d1a5b8171918319fe623d11995983c940eb2121a4725","response-headers":{"Accept-Ranges":"bytes","Access-Control-Allow-Origin":"*","Cache-Control":"max-age=300","Connection":"keep-alive","Content-Encoding":"gzip","Content-Length":"201","Content-Security-Policy":"default-src 'none'; style-src 'unsafe-inline'; sandbox","Content-Type":"text/plain; charset=utf-8","Cross-Origin-Resource-Policy":"cross-origin","Date":"Thu, 18 Jan 2024 00:07:31 GMT","ETag":"W/\"812beffb238e531b5d72ee12a256ad0eabd92a880a69be0064de7cd14f1eebff\"","Expires":"Thu, 18 Jan 2024 00:12:31 GMT","Source-Age":"0","Strict-Transport-Security":"max-age=31536000","Vary":"Authorization,Accept-Encoding,Origin","Via":"1.1 varnish","X-Cache":"MISS","X-Cache-Hits":"0","X-Content-Type-Options":"nosniff","X-Fastly-Request-ID":"4fc666f9ff7e39f5c5c3e51c3afa9a6981f31361","X-Frame-Options":"deny","X-GitHub-Request-Id":"37FC:92B3:E6B13C:115453F:65A86BC1","X-Served-By":"cache-iad-kcgs7200043-IAD","X-Timer":"S1705536451.466825,VS0,VE66","X-XSS-Protection":"1; mode=block"},"ssl-verify":true,"status":"200"}