{"elapsed":"0.395","endpoint-url":"https://www.registers.service.gov.uk/registers/internal-drainage-board/download-csv","entry-date":"2021-01-31T00:18:47.275223","request-headers":{"Accept":"*/*","Accept-Encoding":"gzip, deflate","Connection":"keep-alive","Cookie":"seen_cookie_message=true","User-Agent":"Digital Land"},"resource":"af14ba711cb80895ee847e45189536e93685e7b0875aa9448c783072ce0e25d7","response-headers":{"Cache-Control":"private","Connection":"keep-alive","Content-Disposition":"attachment; filename=internal-drainage-board.csv","Content-Transfer-Encoding":"binary","Content-Type":"application/csv; header=present","Date":"Sun, 31 Jan 2021 00:18:49 GMT","ETag":"W/\"af14ba711cb80895ee847e45189536e9\"","Referrer-Policy":"strict-origin-when-cross-origin","Set-Cookie":"seen_cookie_message=true; path=/; expires=Mon, 31 Jan 2022 00:18:49 GMT","Strict-Transport-Security":"max-age=31536000; includeSubDomains; preload","Transfer-Encoding":"chunked","Via":"1.1 c1802b2f6f4e591b6df12b5a8a9876a7.cloudfront.net (CloudFront)","X-Amz-Cf-Id":"B37BQu3TQONTdEck7NgE0up3413cb4fmPKq3UzJtpzQlrHUUrtBKVg==","X-Amz-Cf-Pop":"IAD89-C1","X-Cache":"Miss from cloudfront","X-Content-Type-Options":"nosniff","X-Download-Options":"noopen","X-Frame-Options":"SAMEORIGIN","X-Permitted-Cross-Domain-Policies":"none","X-Request-Id":"56f4d231-2b4d-4b71-8f55-30fc96844906","X-Runtime":"0.135680","X-Vcap-Request-Id":"de31c86b-d6b8-4208-7a78-b0c8640a6995","X-Xss-Protection":"1; mode=block"},"ssl-verify":true,"status":"200"}